{
  "title": "加熱煙專區",
  "slug": "e-cigarette",
  "url": "https://www.bababoitw8.com/e-cigarette",
  "ctaLabel": "詳細資料",
  "products": [
    {
      "slug": "iluma-one-i-8代",
      "t1": "ILUMA ONE i 8代",
      "d1": "8代IQOS主機一體機",
      "d2": "適配TEREA加熱煙彈",
      "price": "$2000",
      "img": "a14f67_fc20067225344272b3041f6d6a8710a3~mv2.jpg",
      "description": "適配 台/日/韓 所有TEREA煙彈\n\n一體設計 : 主機+電池整合 方便攜帶\n20次連抽 : 內建1728mAh電池\n快速充電 : 充滿電約90分鐘 \n輕巧好握 : 底部防滑, 輕鬆單手操作",
      "gallery": [
        "a14f67_fc20067225344272b3041f6d6a8710a3~mv2.jpg",
        "a14f67_3579a5cb07c447e4892106edc82b6f16~mv2.jpg"
      ],
      "variants": []
    },
    {
      "slug": "leme-煙彈",
      "t1": "(日版) 樂美 LEME煙彈",
      "d1": "通用 IQOS 3.0 2.4",
      "d2": "ISMOD II PLUS/NANO",
      "price": "$1000",
      "img": "a14f67_5bfd8606cceb4e52af840acf6f27e508~mv2.jpg",
      "description": "✨經典系列 $1000\n【原味】 涼度☆☆☆\n【薄荷】 涼度★★☆\n【檸檬】 涼度★★☆\n【哈密​​瓜】 涼度★☆☆\n【莫吉托】 涼度★★★\n【橘子冰】 涼度★★☆\n【葡萄】涼度★☆☆\n🔍探索系列 $1000\n【紫葡萄➕】涼度★★☆\n【西柚】 涼度★★★\n【咖啡】 涼度☆☆☆\n【抹茶】 涼度★★☆\n【黑冰】 涼度★★★\n💥爆珠系列 $1000\n【藍莓】 涼度★★★\n【話梅】 涼度★☆☆\n【堅果】 涼度☆☆☆\n【檸檬之淚 】 涼度★★☆\n濃原味系列\n【濃原味】 涼度☆☆☆ $1000\n【濃原味➕】 涼度☆☆☆ $1000\n\n【暫時缺貨 | 待補貨商品】\n西柚\n紫葡萄+\n濃原味+\n檸檬之淚",
      "gallery": [
        "a14f67_1f0e613e0b95415fa6b6111dcfd20fef~mv2.jpg",
        "a14f67_3a4f822311ad4773b905cbef64d91dab~mv2.jpg",
        "a14f67_5e1aed5129ef4f6eaabae5db6b7b2808~mv2.jpg",
        "a14f67_1decde271ca74fc182a9a8648bb83820~mv2.jpg",
        "a14f67_97ed7beedb544e90b038e872e5d0cee8~mv2.jpg",
        "a14f67_14210ff61be147478f0590947914099b~mv2.jpg",
        "a14f67_4a7ba83a791d470bafae4abfb00a4e12~mv2.jpg",
        "a14f67_b1015c1ab41642c99240d981d8b357eb~mv2.jpg",
        "a14f67_b23e5c86b7fc46c3a8059635614aa70d~mv2.jpg",
        "a14f67_3184bb53e4f04ccf93002d45bde8442b~mv2.jpg",
        "a14f67_5bfd8606cceb4e52af840acf6f27e508~mv2.jpg"
      ],
      "variants": []
    },
    {
      "slug": "【新品】ploom-aura-主機",
      "t1": "【新品】Ploom Aura 主機",
      "d1": "【新品入荷】",
      "d2": "七星煙彈主機",
      "price": "$請洽客服",
      "img": "a14f67_075c25d5cf3e49bca7fd5e5e2984ab44~mv2.jpg",
      "description": "Ploom Aura !!新品入荷!!\n改變過往加熱煙主機的新形態智慧型主機\n\n最長 6 分鐘盡情享受，次數不設限。\n搭載「SMART HEATFLOW」智慧加熱技術，完整釋放菸草本味；再加上全新高密度菸草棒，讓每一口從開始到最後，都濃郁、紮實，滿足不打折。\n\nSMART HEATFLOW\n\n什麼是「SMART HEATFLOW」?\n\n在 320 度下，抑制加熱所產生的雜味與焦焦氣味，同時完美釋放菸草的香韻。\n透過 SMART HEATFLOW 長時間維持最高加熱溫度，讓風味更加一致穩定。\n此外，加熱杯以微米級精度加工，將加熱效率發揮到極致。\n椭圓狀的杯體設計，增加與菸草棒的接觸面積，將菸草本味毫無保留地釋放。\n\n依照喜好，自由選擇每一口的體驗\n全新搭載「HEAT SELECT SYSTEM」，可調整吸入感的強弱與使用時間，享受最合你心意的一口。\n\nStandard Mode（標準模式）\n\n平衡度最佳，彷彿融合了所有模式的平均值。\n強度：●●〇　/　使用時間：約 5 分鐘　/　可用次數：約 20 次\n\nStrong Mode（強勁模式）\n\n吸入感最強，從第一口就能感受到滿滿的滿足感。\n強度：●●●　/　使用時間：約 3 分鐘　/　可用次數：約 25 次\n\nLong Mode（長效模式）\n\n可以悠閒慢吸，不易膩口，適合想要久一點的體驗。\n強度：●〇〇　/　使用時間：約 6 分鐘　/　可用次數：約 19 次\n\nEco Mode（省電模式）\n\n適合想快速獲得滿足感的人，每次充電可使用次數最多。\n強度：●●〇　/　使用時間：約 3 分鐘　/　可用次數：約 27 次\n\n設備尺寸\n寬度 24.2mm x 高度 109.4mm x 深度 29.2mm\n約77.9g\n\n充電方式\nType-C",
      "gallery": [
        "a14f67_075c25d5cf3e49bca7fd5e5e2984ab44~mv2.jpg",
        "a14f67_d6a844cdbd8b4970b912984b633a9228~mv2.jpg",
        "a14f67_d269f8d47a2140389933e6a2cf18c69f~mv2.jpg",
        "a14f67_8c9cc46e0d05479cba8abb409d0227c4~mv2.jpg",
        "a14f67_aff71cbf8b4e4dc7847071da8af887f3~mv2.jpg",
        "a14f67_3666584b53944c61bf326630c9f67ed2~mv2.jpg",
        "a14f67_91af62d8b68b4ecda1ec019292e8cc62~mv2.jpg"
      ],
      "variants": []
    },
    {
      "slug": "ismod-ii-plus",
      "t1": "ISMOD II PLUS",
      "d1": "通用 LEME樂美 H牌 M牌",
      "d2": "IQOS 3.0 2.4 雙單桿",
      "price": "$2550",
      "img": "a14f67_b71670bc8c034368bc219c516aee7ab9~mv2.jpg",
      "description": "通用 LEME樂美 H牌 M牌 / IQOS 3.0 2.4 雙單桿\n\n產品規格：\n配置：雙桿+移動電源\n電池類型：高倍率鋰電池\n棒電池容量：160mah\n充電器電池容量：2600mAh\n充電模式：快速充電\n使用時間：260s\n預熱時間：<15s\n加熱溫度：320℃-350 ℃\n\n內容物：\n加熱棒*2\n充電盒*1\n清潔用具*1\n棉花棒*1\n充電線*1\n一個設備，兩個支架，提供雙重享受。",
      "gallery": [
        "a14f67_afc357c7b00f427bb355a0781fc90abf~mv2.jpg",
        "a14f67_9c2aea5eea6141e3a9fb6d4931ee4848~mv2.jpg",
        "a14f67_cade671b19dd4d8793d03e0aa980121f~mv2.jpg",
        "a14f67_b71670bc8c034368bc219c516aee7ab9~mv2.jpg",
        "a14f67_215bea9793224cfd9be3fe17162507f2~mv2.jpg",
        "a14f67_3c8f78c59d1c4f26b43392e15654adcd~mv2.jpg"
      ],
      "variants": []
    },
    {
      "slug": "【熱銷】terea-(日版t牌)",
      "t1": "【熱銷】TEREA (日版T牌)",
      "d1": "✨大盤商獨家販售✨",
      "d2": "ILUMA機型專用煙彈",
      "price": "口味/價格請洽客服",
      "img": "a14f67_37cead032cfc40558cf4df8e0efdfa78~mv2.jpg",
      "description": "適配 IQOS ILUMA 機型",
      "gallery": [
        "a14f67_1d76bae8d7ff4b9f852e852dd2712324~mv2.jpg",
        "a14f67_20255872093d4905b04beb416b39e1be~mv2.webp",
        "a14f67_bfd1d9bf97744209bf042e97f6ddf492~mv2.webp",
        "a14f67_609a8ddf3b404fdf9133b4c40bce0ee0~mv2.png"
      ],
      "variants": []
    },
    {
      "slug": "【新品】leme-sheen",
      "t1": "LEME SHEEN 樂美ＰＲＯ",
      "d1": "自動清潔｜四段調溫",
      "price": "$1000",
      "img": "a14f67_384ed42f9929440999beb566a29a1f8e~mv2.jpg",
      "description": "【新品到著】\nLEME SHEEN | 樂美 PRO\n\n功能說明：\n1. 自動清潔\n2. 四段調溫\n3. 震動提示\n4. 快拆清潔\n\n調溫模式：\n快速連按主鍵4次進入調溫模式\n共4檔 指示燈1-4 (從下到上)\n\n電量顯示：\n4格: 100%\n3格: 75%-100%\n2格: 50%-75%\n1格: ＜25%\n\n產品規格：\n電池容量：1600mAh\n充電時間：≤90分鐘\n充電方式：USB接口-Type C\n預熱時間：15秒\n工作時間：15口/300秒\n產品尺寸：24x18x102.5mm\n產品淨重：56g\n續行時長：≥20支\n\n內容物：\n主機*1 \n清潔工具*5\nType-C充電線*1\n產品說明書*1",
      "gallery": [
        "a14f67_384ed42f9929440999beb566a29a1f8e~mv2.jpg",
        "a14f67_24fe8cfe5af74203ae23da5aba04f8b7~mv2.jpg",
        "a14f67_1bbe7c71dbe94f77af8911fadaf251c2~mv2.jpg",
        "a14f67_53d199887ba14b14894fc23a84d128b1~mv2.jpg",
        "a14f67_1bf97ae9c1a14fd48ebdf035e6f9314e~mv2.jpg",
        "a14f67_fb05fc79e3e847a889f189b3c437fa83~mv2.jpg"
      ],
      "variants": []
    },
    {
      "slug": "【新品】日版七星加熱煙",
      "t1": "【新品】 七星煙彈",
      "d1": "日本七星煙彈",
      "d2": "Ploom X 主機使用",
      "price": "$請洽客服",
      "img": "a14f67_23d882168a1547f3a127664b4cd056cc~mv2.jpg",
      "description": "七星加熱煙彈\n\n專為 Ploom X 設備設計的七星煙彈\n融合清爽舒適的吸菸感受\n完美詮釋七星一貫的經典風味\n成就獨特品味時刻\n\n敬請期待新口味...",
      "gallery": [
        "a14f67_d6b91e51f854424e8a468d7773d80a41~mv2.jpg",
        "a14f67_8457a2ba3cd148cf8119aced6ea3043b~mv2.jpg",
        "a14f67_23d882168a1547f3a127664b4cd056cc~mv2.jpg",
        "a14f67_8e65ac55fa454cbba2f4772aece59378~mv2.jpg"
      ],
      "variants": []
    },
    {
      "slug": "ismod-nano",
      "t1": "ISMOD NANO",
      "d1": "通用 IQOS 3.0 2.4",
      "d2": "LEME樂美 H牌 M牌",
      "price": "$1550",
      "img": "a14f67_eaf38201aafa4ff2b81e9aeed6d980d8~mv2.jpg",
      "description": "通用 IQOS 3.0 2.4 LEME樂美 H牌 M牌 煙彈\n\n功能說明：\n1.自行更換加熱棒、零件\n2.3段調溫\n3.震動提示\n4.快速關機\n5.異常重置\n6.快拆清潔\n調溫模式：\n快速連按主鍵5次進入調溫模式\n綠色：低檔\n白色：中檔\n紫色：高檔\n電量顯示：\n藍色：60%-100%\n黃色：10%-60%\n紅色：0%-10%\n產品規格：\n電池容量：1500毫安，3.7V\n充電時間：1.5小時\n充電方式：USB插口-Type C\n預熱時間：15秒\n工作時間：15口或300秒\n產品尺寸：27mm(寬)x17mm(厚)x90mm(高)\n產品重量：51克\n滿電使用：約20支",
      "gallery": [
        "a14f67_e2fd2b6220194d1fbc992180cc36d69d~mv2.jpg",
        "a14f67_9c260182768148c1b1b7426f4aae7279~mv2.png",
        "a14f67_0cbb21f56bc3447fa11e0ab84d57dd88~mv2.jpg",
        "a14f67_f64c2fa7163a41b88860e95dbb4525a6~mv2.jpg",
        "a14f67_0d57716a50184c068559243bc9b1ac16~mv2.jpg",
        "a14f67_16c8f1a95074487cb120a6f225150de4~mv2.jpg"
      ],
      "variants": []
    },
    {
      "slug": "美版-leme煙彈",
      "t1": "(美版) 樂美 LEME煙彈",
      "d1": "美版包裝隆重登場",
      "d2": "全新風格引領潮流",
      "price": "$1000",
      "img": "a14f67_3380ee53ef604c0fa1514928fcb6fd91~mv2.jpg",
      "description": "美版LEME (通用3.0規格)\n$1000\n\n原味\n濃原味\n薄荷\n檸檬\n藍莓爆珠\n\n其他口味還在游泳~~~~~\n殷切期待!!!",
      "gallery": [
        "a14f67_ac124e8aed25410f84d4b066de224c97~mv2.jpg",
        "a14f67_b73c4b7b27cc448cb0033b2a34782d74~mv2.jpg",
        "a14f67_e446a5731e03407ea4df8bb3ba19d9c7~mv2.jpg",
        "a14f67_76c4d1e5570542af8fe1e460ac5eda5b~mv2.jpg"
      ],
      "variants": []
    },
    {
      "slug": "leme-sip",
      "t1": "LEME SIP",
      "d1": "通用3.0規格煙彈",
      "d2": "LEME煙彈 M牌 H牌",
      "price": "$1350",
      "img": "a14f67_10d656e876764eeb97255f14c7890828~mv2.jpg",
      "description": "產品特色：\n精準溫度控制≤±5℃，實時進行高頻採樣，激發醇粹口感與香韻\n設備重量僅有46g，日常攜帶超級便利\n一次充電續航 10 支，每根煙彈提供 14 口/5 分鐘的加熱時長\n設計簡約，帶隱藏式Type-c充電口\n橡膠柔軟觸感塗料，表面光滑，極致手感\n類似IQOS的加熱刀片，加熱熱面積更大，可拆卸加熱倉，易於清潔\n創新的波浪形氣道設計降低了夾緊香煙時的吸力阻力\n通用煙彈 T牌TEREA | M牌 Marlboro | H牌 Heets | MOTX | ZERO | cigoo\n \n產品規格：\n尺寸：94.5×27.1×15.1(mm)\n重量：46g\n電量：940mAh\n充電時間：約70分鐘\n預熱時間：20秒\n加熱溫度：﹤300℃\n正常電量:50-100%（白燈）    即將需要充電:0-50%（黃燈）",
      "gallery": [
        "a14f67_f16b024ddf694d598c4b868d6142e9bf~mv2.jpg",
        "a14f67_e9e9a9ef5ac049d6880177d854cf0d26~mv2.jpg",
        "a14f67_cfc027407bcd43bcbc4b0d9ead9c83b4~mv2.jpg",
        "a14f67_10d656e876764eeb97255f14c7890828~mv2.jpg",
        "a14f67_c75011d246d64fb297563c729af98f0b~mv2.jpg",
        "a14f67_a836984c43894a8688c643fbfced6256~mv2.jpg",
        "a14f67_32f0faeb8f374ff7b30fb8c368aa94fd~mv2.jpg"
      ],
      "variants": []
    },
    {
      "slug": "ismod-blaze",
      "t1": "ISMOD BLAZE",
      "d1": "通用T牌｜LEME 電磁原味",
      "d2": "4.0規格主機｜電磁加熱系統",
      "price": "$2500",
      "img": "a14f67_5037965394a14981b790f0f8e55f0b27~mv2.png",
      "description": "4.0規格主機 \n通用：\nIQOS TEREA煙彈 (T牌)\nLEME 電磁原味\n\n電磁加熱系統 TYPE-C充電 高續航力\n滿電狀態可支援20+支煙彈\n\n重量：56g\n電量：1500mha\n尺寸：89*28*18mm\n\n內容物：\nISMOD Blaze主機*1、Type-C充電線*1、清潔棒*1、使用說明書*1",
      "gallery": [
        "a14f67_5037965394a14981b790f0f8e55f0b27~mv2.png",
        "a14f67_b4e8b6b342794382a0d5b096470325f6~mv2.png",
        "a14f67_5aa7891731954ca5b56e0cd887010b36~mv2.png",
        "a14f67_38671eee74ed414b9d57f870e3b38700~mv2.png",
        "a14f67_83abb2e9910e484a821e53c4c6b07d92~mv2.png",
        "a14f67_e6983f596d564ea2bb26eda4d20b3717~mv2.png",
        "a14f67_4d5771a0705f4304a90aa3ffad9d7ccd~mv2.png"
      ],
      "variants": []
    }
  ]
}